settings_manager/__init__.py
django_settings_manager-0.0.4.dist-info/LICENSE
django_settings_manager-0.0.4.dist-info/METADATA
django_settings_manager-0.0.4.dist-info/WHEEL
django_settings_manager-0.0.4.dist-info/top_level.txt
django_settings_manager-0.0.4.dist-info/RECORD
