Metadata-Version: 2.1
Name: django-settings-manager
Version: 0.0.4
Summary: A simple, extensible YAML-based configuration strategy for Django
Home-page: https://github.com/ihadgraft/django-settings-manager
Author: Iain Hadgraft
Author-email: ihadgraft@gmail.com
License: UNKNOWN
Platform: UNKNOWN
Classifier: Programming Language :: Python :: 3
Classifier: License :: OSI Approved :: Apache Software License
Classifier: Operating System :: OS Independent
Requires-Dist: pyyaml (>=5.1)
Requires-Dist: deepmerge
Provides-Extra: dev
Requires-Dist: pytest ; extra == 'dev'
